{
  "annotations": {
    "list": [
      {
        "builtIn": 1,
        "datasource": {
          "type": "grafana",
          "uid": "-- Grafana --"
        },
        "enable": true,
        "hide": true,
        "iconColor": "rgba(0, 211, 255, 1)",
        "name": "Annotations & Alerts",
        "type": "dashboard"
      }
    ]
  },
  "description": "Метрики работы c библиотекой взаимодействия с MS AD.",
  "editable": true,
  "fiscalYearStartMonth": 0,
  "graphTooltip": 0,
  "links": [],
  "panels": [
    {
      "collapsed": false,
      "gridPos": {
        "h": 1,
        "w": 24,
        "x": 0,
        "y": 0
      },
      "id": 9,
      "panels": [],
      "title": "Authentication counts",
      "type": "row"
    },
    {
      "datasource": {
        "type": "prometheus",
        "uid": "prometheus"
      },
      "fieldConfig": {
        "defaults": {
          "color": {
            "mode": "thresholds"
          },
          "mappings": [],
          "thresholds": {
            "mode": "absolute",
            "steps": [
              {
                "color": "green",
                "value": null
              }
            ]
          }
        },
        "overrides": []
      },
      "gridPos": {
        "h": 4,
        "w": 4,
        "x": 0,
        "y": 1
      },
      "id": 7,
      "options": {
        "colorMode": "value",
        "graphMode": "none",
        "justifyMode": "auto",
        "orientation": "auto",
        "percentChangeColorMode": "standard",
        "reduceOptions": {
          "calcs": [
            "lastNotNull"
          ],
          "fields": "",
          "values": false
        },
        "showPercentChange": false,
        "textMode": "auto",
        "wideLayout": true
      },
      "pluginVersion": "11.5.0",
      "targets": [
        {
          "datasource": {
            "type": "prometheus",
            "uid": "prometheus"
          },
          "editorMode": "code",
          "expr": "auth_successful_count_total{application=\"Ovis\",instance=\"$instance\"}",
          "instant": false,
          "legendFormat": "__auto",
          "range": true,
          "refId": "A"
        }
      ],
      "title": "Success auth count total",
      "type": "stat"
    },
    {
      "datasource": {
        "type": "prometheus",
        "uid": "prometheus"
      },
      "fieldConfig": {
        "defaults": {
          "color": {
            "mode": "palette-classic"
          },
          "custom": {
            "hideFrom": {
              "legend": false,
              "tooltip": false,
              "viz": false
            }
          },
          "fieldMinMax": false,
          "mappings": [],
          "min": 0
        },
        "overrides": [
          {
            "matcher": {
              "id": "byName",
              "options": "Failed"
            },
            "properties": [
              {
                "id": "color",
                "value": {
                  "fixedColor": "red",
                  "mode": "fixed"
                }
              }
            ]
          },
          {
            "matcher": {
              "id": "byName",
              "options": "Success"
            },
            "properties": [
              {
                "id": "color",
                "value": {
                  "fixedColor": "green",
                  "mode": "fixed"
                }
              }
            ]
          },
          {
            "matcher": {
              "id": "byName",
              "options": "Timeout"
            },
            "properties": [
              {
                "id": "color",
                "value": {
                  "fixedColor": "light-blue",
                  "mode": "fixed"
                }
              }
            ]
          }
        ]
      },
      "gridPos": {
        "h": 12,
        "w": 4,
        "x": 4,
        "y": 1
      },
      "id": 11,
      "options": {
        "displayLabels": [],
        "legend": {
          "displayMode": "table",
          "placement": "bottom",
          "showLegend": true,
          "values": [
            "percent"
          ]
        },
        "pieType": "pie",
        "reduceOptions": {
          "calcs": [],
          "fields": "",
          "values": false
        },
        "tooltip": {
          "hideZeros": false,
          "mode": "single",
          "sort": "none"
        }
      },
      "pluginVersion": "11.5.0",
      "targets": [
        {
          "datasource": {
            "type": "prometheus",
            "uid": "prometheus"
          },
          "editorMode": "code",
          "expr": "auth_successful_count_total{application=\"Ovis\",instance=\"$instance\"}",
          "interval": "",
          "legendFormat": "Success",
          "range": true,
          "refId": "A"
        },
        {
          "datasource": {
            "type": "prometheus",
            "uid": "prometheus"
          },
          "editorMode": "code",
          "expr": "auth_timeout_count_total{application=\"Ovis\",instance=\"$instance\"}",
          "hide": false,
          "instant": false,
          "legendFormat": "Timeout",
          "range": true,
          "refId": "C"
        },
        {
          "datasource": {
            "type": "prometheus",
            "uid": "prometheus"
          },
          "editorMode": "code",
          "expr": "auth_failed_count_total{application=\"Ovis\",instance=\"$instance\"}",
          "hide": false,
          "instant": false,
          "legendFormat": "Failed",
          "range": true,
          "refId": "B"
        }
      ],
      "title": "",
      "type": "piechart"
    },
    {
      "datasource": {
        "type": "prometheus",
        "uid": "prometheus"
      },
      "fieldConfig": {
        "defaults": {
          "color": {
            "mode": "palette-classic"
          },
          "custom": {
            "axisBorderShow": true,
            "axisCenteredZero": false,
            "axisColorMode": "text",
            "axisLabel": "",
            "axisPlacement": "auto",
            "barAlignment": 0,
            "barWidthFactor": 0.6,
            "drawStyle": "line",
            "fillOpacity": 10,
            "gradientMode": "opacity",
            "hideFrom": {
              "legend": false,
              "tooltip": false,
              "viz": false
            },
            "insertNulls": false,
            "lineInterpolation": "linear",
            "lineStyle": {
              "fill": "solid"
            },
            "lineWidth": 2,
            "pointSize": 5,
            "scaleDistribution": {
              "type": "linear"
            },
            "showPoints": "auto",
            "spanNulls": false,
            "stacking": {
              "group": "A",
              "mode": "none"
            },
            "thresholdsStyle": {
              "mode": "off"
            }
          },
          "mappings": [],
          "min": 0,
          "thresholds": {
            "mode": "absolute",
            "steps": [
              {
                "color": "green",
                "value": null
              }
            ]
          },
          "unit": "short"
        },
        "overrides": [
          {
            "matcher": {
              "id": "byName",
              "options": "failed auth count "
            },
            "properties": [
              {
                "id": "color",
                "value": {
                  "fixedColor": "red",
                  "mode": "fixed"
                }
              }
            ]
          },
          {
            "matcher": {
              "id": "byName",
              "options": "timeout error count"
            },
            "properties": [
              {
                "id": "color",
                "value": {
                  "fixedColor": "light-blue",
                  "mode": "fixed"
                }
              }
            ]
          }
        ]
      },
      "gridPos": {
        "h": 12,
        "w": 15,
        "x": 8,
        "y": 1
      },
      "id": 4,
      "options": {
        "legend": {
          "calcs": [
            "lastNotNull",
            "max",
            "mean"
          ],
          "displayMode": "table",
          "placement": "bottom",
          "showLegend": true
        },
        "tooltip": {
          "hideZeros": false,
          "mode": "single",
          "sort": "none"
        }
      },
      "pluginVersion": "11.5.0",
      "targets": [
        {
          "datasource": {
            "type": "prometheus",
            "uid": "prometheus"
          },
          "editorMode": "code",
          "expr": "rate(auth_successful_count_total{instance=\"$instance\"}[$__rate_interval])",
          "hide": false,
          "instant": false,
          "legendFormat": "success auth count",
          "range": true,
          "refId": "C"
        },
        {
          "datasource": {
            "type": "prometheus",
            "uid": "prometheus"
          },
          "editorMode": "code",
          "expr": "rate(auth_failed_count_total{instance=\"$instance\"}[$__rate_interval])",
          "hide": false,
          "instant": false,
          "legendFormat": "failed auth count ",
          "range": true,
          "refId": "B"
        },
        {
          "datasource": {
            "type": "prometheus",
            "uid": "prometheus"
          },
          "disableTextWrap": false,
          "editorMode": "code",
          "expr": "rate(auth_timeout_count_total{instance=\"$instance\"}[$__rate_interval])",
          "fullMetaSearch": false,
          "includeNullMetadata": true,
          "legendFormat": "timeout error count",
          "range": true,
          "refId": "A",
          "useBackend": false
        }
      ],
      "title": "Auth counts (rate)",
      "type": "timeseries"
    },
    {
      "datasource": {
        "type": "prometheus",
        "uid": "prometheus"
      },
      "fieldConfig": {
        "defaults": {
          "color": {
            "mode": "thresholds"
          },
          "mappings": [],
          "thresholds": {
            "mode": "absolute",
            "steps": [
              {
                "color": "red",
                "value": null
              }
            ]
          }
        },
        "overrides": []
      },
      "gridPos": {
        "h": 4,
        "w": 4,
        "x": 0,
        "y": 5
      },
      "id": 5,
      "options": {
        "colorMode": "value",
        "graphMode": "none",
        "justifyMode": "auto",
        "orientation": "auto",
        "percentChangeColorMode": "standard",
        "reduceOptions": {
          "calcs": [
            "lastNotNull"
          ],
          "fields": "",
          "values": false
        },
        "showPercentChange": false,
        "textMode": "auto",
        "wideLayout": true
      },
      "pluginVersion": "11.5.0",
      "targets": [
        {
          "datasource": {
            "type": "prometheus",
            "uid": "prometheus"
          },
          "editorMode": "code",
          "expr": "auth_failed_count_total{application=\"Ovis\",instance=\"$instance\"}",
          "instant": false,
          "legendFormat": "__auto",
          "range": true,
          "refId": "A"
        }
      ],
      "title": "Failed auth count total",
      "type": "stat"
    },
    {
      "datasource": {
        "type": "prometheus",
        "uid": "prometheus"
      },
      "fieldConfig": {
        "defaults": {
          "color": {
            "mode": "thresholds"
          },
          "mappings": [],
          "thresholds": {
            "mode": "absolute",
            "steps": [
              {
                "color": "blue",
                "value": null
              }
            ]
          }
        },
        "overrides": []
      },
      "gridPos": {
        "h": 4,
        "w": 4,
        "x": 0,
        "y": 9
      },
      "id": 6,
      "options": {
        "colorMode": "value",
        "graphMode": "none",
        "justifyMode": "auto",
        "orientation": "auto",
        "percentChangeColorMode": "standard",
        "reduceOptions": {
          "calcs": [
            "lastNotNull"
          ],
          "fields": "",
          "values": false
        },
        "showPercentChange": false,
        "textMode": "auto",
        "wideLayout": true
      },
      "pluginVersion": "11.5.0",
      "targets": [
        {
          "datasource": {
            "type": "prometheus",
            "uid": "prometheus"
          },
          "editorMode": "code",
          "expr": "auth_timeout_count_total{application=\"Ovis\",instance=\"$instance\"}",
          "instant": false,
          "legendFormat": "__auto",
          "range": true,
          "refId": "A"
        }
      ],
      "title": "Timeout auth count total",
      "type": "stat"
    },
    {
      "collapsed": false,
      "gridPos": {
        "h": 1,
        "w": 24,
        "x": 0,
        "y": 13
      },
      "id": 12,
      "panels": [],
      "title": "Authentication duration",
      "type": "row"
    },
    {
      "datasource": {
        "type": "prometheus",
        "uid": "prometheus"
      },
      "description": "",
      "fieldConfig": {
        "defaults": {
          "color": {
            "mode": "palette-classic"
          },
          "custom": {
            "axisBorderShow": false,
            "axisCenteredZero": false,
            "axisColorMode": "text",
            "axisLabel": "",
            "axisPlacement": "auto",
            "barAlignment": 0,
            "barWidthFactor": 0.6,
            "drawStyle": "line",
            "fillOpacity": 10,
            "gradientMode": "opacity",
            "hideFrom": {
              "legend": false,
              "tooltip": false,
              "viz": false
            },
            "insertNulls": false,
            "lineInterpolation": "linear",
            "lineStyle": {
              "fill": "solid"
            },
            "lineWidth": 2,
            "pointSize": 5,
            "scaleDistribution": {
              "type": "linear"
            },
            "showPoints": "auto",
            "spanNulls": false,
            "stacking": {
              "group": "A",
              "mode": "none"
            },
            "thresholdsStyle": {
              "mode": "off"
            }
          },
          "mappings": [],
          "min": 0,
          "thresholds": {
            "mode": "absolute",
            "steps": [
              {
                "color": "green",
                "value": null
              }
            ]
          },
          "unit": "ms"
        },
        "overrides": [
          {
            "matcher": {
              "id": "byName",
              "options": "quantile = 0.99"
            },
            "properties": [
              {
                "id": "color",
                "value": {
                  "fixedColor": "purple",
                  "mode": "fixed"
                }
              }
            ]
          },
          {
            "matcher": {
              "id": "byName",
              "options": "quantile = 0.5"
            },
            "properties": [
              {
                "id": "color",
                "value": {
                  "fixedColor": "semi-dark-orange",
                  "mode": "fixed"
                }
              }
            ]
          },
          {
            "matcher": {
              "id": "byName",
              "options": "quantile = 0.95"
            },
            "properties": [
              {
                "id": "color",
                "value": {
                  "fixedColor": "yellow",
                  "mode": "fixed"
                }
              }
            ]
          }
        ]
      },
      "gridPos": {
        "h": 13,
        "w": 23,
        "x": 0,
        "y": 14
      },
      "id": 1,
      "options": {
        "legend": {
          "calcs": [
            "min",
            "max",
            "mean"
          ],
          "displayMode": "table",
          "placement": "right",
          "showLegend": true
        },
        "tooltip": {
          "hideZeros": false,
          "mode": "single",
          "sort": "none"
        }
      },
      "pluginVersion": "11.5.0",
      "targets": [
        {
          "datasource": {
            "type": "prometheus",
            "uid": "prometheus"
          },
          "disableTextWrap": false,
          "editorMode": "code",
          "expr": "auth_process_time_seconds{quantile=\"0.5\",instance=\"$instance\"} ",
          "format": "time_series",
          "fullMetaSearch": false,
          "includeNullMetadata": true,
          "interval": "",
          "legendFormat": "quantile = 0.5",
          "range": true,
          "refId": "A",
          "useBackend": false
        },
        {
          "datasource": {
            "type": "prometheus",
            "uid": "prometheus"
          },
          "editorMode": "code",
          "expr": "auth_process_time_seconds{quantile=\"0.95\",instance=\"$instance\"}",
          "hide": false,
          "instant": false,
          "legendFormat": "quantile = 0.95",
          "range": true,
          "refId": "B"
        },
        {
          "datasource": {
            "type": "prometheus",
            "uid": "prometheus"
          },
          "editorMode": "code",
          "expr": "auth_process_time_seconds{quantile=\"0.99\",instance=\"$instance\"}",
          "hide": false,
          "instant": false,
          "legendFormat": "quantile = 0.99",
          "range": true,
          "refId": "C"
        }
      ],
      "title": "Authentication duration",
      "type": "timeseries"
    }
  ],
  "preload": false,
  "refresh": "10s",
  "schemaVersion": 40,
  "tags": [],
  "templating": {
    "list": [
      {
        "datasource": {
          "type": "prometheus",
          "uid": "prometheus"
        },
        "definition": "label_values(host)",
        "label": "instance",
        "name": "instance",
        "options": [],
        "query": {
          "qryType": 1,
          "query": "label_values(host)",
          "refId": "PrometheusVariableQueryEditor-VariableQuery"
        },
        "refresh": 1,
        "regex": "",
        "type": "query"
      }
    ]
  },
  "time": {
    "from": "now-1h",
    "to": "now"
  },
  "timepicker": {},
  "timezone": "browser",
  "title": "MS AD",
  "version": 9,
  "weekStart": ""
}
